Adafruit_I2C.py
CHANGELOG.md
MANIFEST.in
README.md
distribute_setup.py
setup.py
Adafruit_BBIO/Encoder.py
Adafruit_BBIO/__init__.py
Adafruit_BBIO.egg-info/PKG-INFO
Adafruit_BBIO.egg-info/SOURCES.txt
Adafruit_BBIO.egg-info/dependency_links.txt
Adafruit_BBIO.egg-info/top_level.txt
overlays/ADAFRUIT-SPI0-00A0.dts
overlays/ADAFRUIT-SPI1-00A0.dts
overlays/ADAFRUIT-UART1-00A0.dts
overlays/ADAFRUIT-UART2-00A0.dts
overlays/ADAFRUIT-UART4-00A0.dts
overlays/ADAFRUIT-UART5-00A0.dts
overlays/__init__.py
overlays/builder.py
source/c_adc.c
source/c_adc.h
source/c_pinmux.c
source/c_pinmux.h
source/c_pwm.c
source/c_pwm.h
source/c_uart.c
source/c_uart.h
source/common.c
source/common.h
source/constants.c
source/constants.h
source/event_gpio.c
source/event_gpio.h
source/py_adc.c
source/py_gpio.c
source/py_pwm.c
source/py_uart.c
source/spimodule.c
source/include/adafruit/bbio.h
source/include/adafruit/bbio/error.h
source/include/adafruit/bbio/gpio.h
source/include/adafruit/bbio/pwm.h
test/test_adc.py
test/test_gpio_input.py
test/test_gpio_output.py
test/test_gpio_setup.py
test/test_led.py
test/test_pwm_setup.py
test/test_rotary.py
test/test_spi.py
test/test_uart.py