Metadata-Version: 1.1
Name: Adafruit-BBIO
Version: 1.0.8
Summary: A module to control BeagleBone IO channels
Home-page: https://github.com/adafruit/adafruit-beaglebone-io-python/
Author: Justin Cooper
Author-email: justin@adafruit.com
License: MIT
Keywords: Adafruit BeagleBone IO GPIO PWM ADC
Platform: UNKNOWN
Classifier: Development Status :: 3 - Alpha
Classifier: Operating System :: POSIX :: Linux
Classifier: License :: OSI Approved :: MIT License
Classifier: Intended Audience :: Developers
Classifier: Programming Language :: Python :: 2.7
Classifier: Programming Language :: Python :: 3
Classifier: Topic :: Software Development
Classifier: Topic :: Home Automation
Classifier: Topic :: System :: Hardware
